docmint/README.md
docmint/__init__.py
docmint/cli.py
docmint/config.py
docmint-0.2.0.dist-info/licenses/LICENSE
docmint-0.2.0.dist-info/METADATA
docmint-0.2.0.dist-info/WHEEL
docmint-0.2.0.dist-info/entry_points.txt
docmint-0.2.0.dist-info/top_level.txt
docmint-0.2.0.dist-info/RECORD
