Metadata-Version: 2.4
Name: docmint
Version: 0.2.0
Summary: 🌟 DocMint: Professional README & Documentation Generator - Transform your projects into professionally documented masterpieces with AI-powered README generation
Home-page: https://github.com/kingsleyesisi/docmint
Author: Kingsley Esisi
Author-email: kingsleyesisi@yahoo.com
License: MIT
Project-URL: Bug Reports, https://github.com/kingsleyesisi/docmint/issues
Project-URL: Source, https://github.com/kingsleyesisi/docmint
Project-URL: Documentation, https://github.com/kingsleyesisi/docmint#readme
Project-URL: Changelog, https://github.com/kingsleyesisi/docmint/releases
Keywords: readme documentation generator markdown cli tool python package ai-powered
Platform: any
Classifier: Development Status :: 4 - Beta
Classifier: Intended Audience :: Developers
Classifier: Topic :: Software Development :: Documentation
Classifier: Topic :: Software Development :: Libraries :: Python Modules
Classifier: Topic :: Text Processing :: Markup :: Markdown
Classifier: Topic :: Utilities
Classifier: License :: OSI Approved :: MIT License
Classifier: Operating System :: OS Independent
Classifier: Environment :: Console
Classifier: Programming Language :: Python :: 3
Classifier: Programming Language :: Python :: 3.8
Classifier: Programming Language :: Python :: 3.9
Classifier: Programming Language :: Python :: 3.10
Classifier: Programming Language :: Python :: 3.11
Classifier: Programming Language :: Python :: 3.12
Classifier: Programming Language :: Python :: 3.13
Classifier: Programming Language :: Python :: 3 :: Only
Requires-Python: >=3.8
License-File: LICENSE
Requires-Dist: click>=8.2.0
Requires-Dist: requests>=2.32.0
Requires-Dist: rich>=13.9.0
Requires-Dist: typer>=0.15.0
Requires-Dist: pydantic>=2.10.0
Requires-Dist: colorama>=0.4.6
Dynamic: author
Dynamic: author-email
Dynamic: classifier
Dynamic: description
Dynamic: description-content-type
Dynamic: home-page
Dynamic: keywords
Dynamic: license
Dynamic: license-file
Dynamic: platform
Dynamic: project-url
Dynamic: requires-dist
Dynamic: requires-python
Dynamic: summary
